scripts/parse_specs.py
velbus_aio-2026.1.4.dist-info/licenses/LICENSE
velbusaio/__init__.py
velbusaio/baseItem.py
velbusaio/channels.py
velbusaio/command_registry.py
velbusaio/const.py
velbusaio/controller.py
velbusaio/discovery.py
velbusaio/exceptions.py
velbusaio/handler.py
velbusaio/helpers.py
velbusaio/message.py
velbusaio/module.py
velbusaio/properties.py
velbusaio/protocol.py
velbusaio/py.typed
velbusaio/raw_message.py
velbusaio/util.py
velbusaio/vlp_reader.py
velbusaio/messages/__init__.py
velbusaio/messages/blind_status.py
velbusaio/messages/bus_active.py
velbusaio/messages/bus_error_counter_status.py
velbusaio/messages/bus_error_counter_status_request.py
velbusaio/messages/bus_off.py
velbusaio/messages/cancel_forced_off.py
velbusaio/messages/cancel_forced_on.py
velbusaio/messages/cancel_inhibit.py
velbusaio/messages/channel_name_part1.py
velbusaio/messages/channel_name_part2.py
velbusaio/messages/channel_name_part3.py
velbusaio/messages/channel_name_request.py
velbusaio/messages/clear_led.py
velbusaio/messages/counter_status.py
velbusaio/messages/counter_status_request.py
velbusaio/messages/counter_value.py
velbusaio/messages/cover_down.py
velbusaio/messages/cover_off.py
velbusaio/messages/cover_position.py
velbusaio/messages/cover_up.py
velbusaio/messages/dali_device_settings.py
velbusaio/messages/dali_device_settings_request.py
velbusaio/messages/dali_dim_value_status.py
velbusaio/messages/dimmer_channel_status.py
velbusaio/messages/dimmer_status.py
velbusaio/messages/edge_set_color.py
velbusaio/messages/edge_set_custom_color.py
velbusaio/messages/fast_blinking_led.py
velbusaio/messages/forced_off.py
velbusaio/messages/forced_on.py
velbusaio/messages/inhibit.py
velbusaio/messages/interface_status_request.py
velbusaio/messages/ir_receiver_status.py
velbusaio/messages/kwh_status.py
velbusaio/messages/light_value_request.py
velbusaio/messages/memo_text.py
velbusaio/messages/memory_data.py
velbusaio/messages/memory_data_block.py
velbusaio/messages/memory_dump_request.py
velbus_aio-2026.1.4.dist-info/METADATA
velbus_aio-2026.1.4.dist-info/WHEEL
velbus_aio-2026.1.4.dist-info/top_level.txt
velbus_aio-2026.1.4.dist-info/RECORD
