Metadata-Version: 2.4
Name: velbus-aio
Version: 2026.1.4
Summary: Open-source home automation platform running on Python 3.
Author-email: Maikel Punie <maikel.punie@gmail.com>
License: MIT
Project-URL: Source Code, https://github.com/Cereal2nd/velbus-aio
Project-URL: Bug Reports, https://github.com/Cereal2nd/velbus-aio/issues
Keywords: home,velbus,automation
Platform: any
Classifier: Development Status :: 5 - Production/Stable
Classifier: Intended Audience :: Developers
Classifier: License :: OSI Approved :: MIT License
Classifier: Natural Language :: English
Classifier: Operating System :: OS Independent
Classifier: Programming Language :: Python :: 3.10
Classifier: Programming Language :: Python :: 3.11
Classifier: Programming Language :: Python :: 3.12
Classifier: Programming Language :: Python :: 3.13
Classifier: Programming Language :: Python :: 3.14
Classifier: Topic :: Home Automation
Classifier: Topic :: Software Development :: Libraries
Classifier: Topic :: Software Development :: Libraries :: Python Modules
Requires-Python: >=3.11.0
License-File: LICENSE
Requires-Dist: pyserial>=3.5.0
Requires-Dist: pyserial-asyncio_fast>=0.11
Requires-Dist: backoff>=1.10.0
Requires-Dist: aiofile
Requires-Dist: beautifulsoup4
Requires-Dist: lxml
Dynamic: license-file
